wake_t/__init__.py
wake_t/beamline_elements/__init__.py
wake_t/beamline_elements/active_plasma_lens.py
wake_t/beamline_elements/beamline.py
wake_t/beamline_elements/field_element.py
wake_t/beamline_elements/field_quadrupole.py
wake_t/beamline_elements/plasma_ramp.py
wake_t/beamline_elements/plasma_stage.py
wake_t/beamline_elements/tm_elements.py
wake_t/diagnostics/__init__.py
wake_t/diagnostics/bunch_analysis.py
wake_t/diagnostics/openpmd_diag.py
wake_t/fields/__init__.py
wake_t/fields/analytical_field.py
wake_t/fields/base.py
wake_t/fields/gather.py
wake_t/fields/interpolation.py
wake_t/fields/numerical_field.py
wake_t/fields/rz_wakefield.py
wake_t/particles/__init__.py
wake_t/particles/deposition.py
wake_t/particles/interpolation.py
wake_t/particles/particle_bunch.py
wake_t/particles/push/__init__.py
wake_t/particles/push/boris_pusher.py
wake_t/particles/push/runge_kutta_4.py
wake_t/particles/push/transfer_matrix.py
wake_t/physics_models/__init__.py
wake_t/physics_models/beam_optics/__init__.py
wake_t/physics_models/beam_optics/transfer_matrices.py
wake_t/physics_models/collective_effects/__init__.py
wake_t/physics_models/collective_effects/csr.py
wake_t/physics_models/em_fields/__init__.py
wake_t/physics_models/em_fields/linear_b_theta.py
wake_t/physics_models/em_fields/quadrupole.py
wake_t/physics_models/laser/__init__.py
wake_t/physics_models/laser/envelope_solver.py
wake_t/physics_models/laser/envelope_solver_non_centered.py
wake_t/physics_models/laser/laser_pulse.py
wake_t/physics_models/laser/tdma.py
wake_t/physics_models/laser/utils.py
wake_t/physics_models/plasma_wakefields/__init__.py
wake_t/physics_models/plasma_wakefields/custom_blowout.py
wake_t/physics_models/plasma_wakefields/focusing_blowout.py
wake_t/physics_models/plasma_wakefields/qs_cold_fluid_1x3p.py
wake_t/physics_models/plasma_wakefields/simple_blowout.py
wake_t/physics_models/plasma_wakefields/qs_rz_baxevanis/__init__.py
wake_t/physics_models/plasma_wakefields/qs_rz_baxevanis/b_theta.py
Wake_T-0.8.0.dist-info/LICENSE
Wake_T-0.8.0.dist-info/METADATA
Wake_T-0.8.0.dist-info/WHEEL
Wake_T-0.8.0.dist-info/top_level.txt
Wake_T-0.8.0.dist-info/RECORD
