Metadata-Version: 2.1
Name: Wake-T
Version: 0.8.0
Summary: A fast particle tracking code for plasma accelerators.
Home-page: https://github.com/AngelFP/Wake-T
Author: Angel Ferran Pousa
Author-email: angel.ferran.pousa@desy.de,
License: GPLv3
Classifier: Development Status :: 3 - Alpha
Classifier: Programming Language :: Python :: 3
Classifier: Intended Audience :: Science/Research
Classifier: Topic :: Scientific/Engineering :: Physics
Classifier: License :: OSI Approved :: GNU General Public License v3 (GPLv3)
Classifier: Operating System :: OS Independent
Requires-Python: >=3.8
License-File: LICENSE
Requires-Dist: numpy
Requires-Dist: numba !=0.57.0
Requires-Dist: scipy
Requires-Dist: aptools ~=0.2.0
Requires-Dist: openpmd-api
Requires-Dist: tqdm
Provides-Extra: test
Requires-Dist: pytest ; extra == 'test'
Requires-Dist: flake8 ; extra == 'test'
Requires-Dist: matplotlib ; extra == 'test'
Requires-Dist: openpmd-viewer ; extra == 'test'
